[{"count": 71, "name": "Aubing-Lochhausen-Langwied", "counter": 73, "relative": 0.9726, "clean": "POOR", "id": 22}, {"count": 350, "name": "Trudering-Riem", "counter": 1346, "relative": 0.26, "clean": "POOR", "id": 15}, {"count": 1156, "name": "Au-Haidhausen", "counter": 12445, "relative": 0.0929, "clean": "POOR", "id": 5}, {"count": 2139, "name": "Untergiesing-Harlaching", "counter": 24900, "relative": 0.0859, "clean": "POOR", "id": 18}, {"count": 1936, "name": "Ramersdorf", "counter": 24401, "relative": 0.0793, "clean": "POOR", "id": 16}, {"count": 1020, "name": "Ludwigsvorstadt-Isarvorstadt", "counter": 13693, "relative": 0.0745, "clean": "POOR", "id": 2}, {"count": 1230, "name": "Schwabing-West", "counter": 16708, "relative": 0.0736, "clean": "POOR", "id": 4}, {"count": 1577, "name": "Thalkirchen-Obersendling-Forstenried-Fuerstenried-Solln", "counter": 22159, "relative": 0.0712, "clean": "POOR", "id": 19}, {"count": 1802, "name": "Bogenhausen", "counter": 25368, "relative": 0.071, "clean": "POOR", "id": 13}, {"count": 526, "name": "Moosach", "counter": 7408, "relative": 0.071, "clean": "POOR", "id": 10}, {"count": 594, "name": "Altstadt-Lehel", "counter": 8592, "relative": 0.0691, "clean": "POOR", "id": 1}, {"count": 1317, "name": "Sendling-Westpark", "counter": 20248, "relative": 0.065, "clean": "POOR", "id": 7}, {"count": 1370, "name": "Milbertshofen-Am", "counter": 21234, "relative": 0.0645, "clean": "POOR", "id": 11}, {"count": 2065, "name": "Schwabing-Freimann", "counter": 32054, "relative": 0.0644, "clean": "POOR", "id": 12}, {"count": 680, "name": "Berg", "counter": 10731, "relative": 0.0634, "clean": "POOR", "id": 14}, {"count": 521, "name": "Pasing-Obermenzing", "counter": 8538, "relative": 0.061, "clean": "POOR", "id": 21}, {"count": 1956, "name": "Neuhausen-Nymphenburg", "counter": 32909, "relative": 0.0594, "clean": "POOR", "id": 9}, {"count": 374, "name": "Schwanthalerhoehe", "counter": 6349, "relative": 0.0589, "clean": "POOR", "id": 8}, {"count": 892, "name": "Maxvorstadt", "counter": 15250, "relative": 0.0585, "clean": "POOR", "id": 3}, {"count": 711, "name": "Obergiesing-Fasangarten", "counter": 12260, "relative": 0.058, "clean": "POOR", "id": 17}, {"count": 479, "name": "Hadern", "counter": 8445, "relative": 0.0567, "clean": "POOR", "id": 20}, {"count": 681, "name": "Sendling", "counter": 12328, "relative": 0.0552, "clean": "POOR", "id": 6}, {"count": 629, "name": "Laim", "counter": 13157, "relative": 0.0478, "clean": "POOR", "id": 25}, {"count": 3, "name": "Feldmoching-Hasenbergl", "counter": 230, "relative": 0.013, "clean": "POOR", "id": 24}]